{
    "property": [
        {
            "companding": "True",
            "compandingAlgorithm": "A-law"
        }
    ],
    "BFA Signatures": [
        {
            "Byte-0": "1.0000000000",
            "Byte-1": "0.8162727563",
            "Byte-2": "0.8029918912",
            "Byte-3": "0.8084280074",
            "Byte-4": "0.8068986778",
            "Byte-5": "0.8079413013",
            "Byte-6": "0.8138665799",
            "Byte-7": "0.8165515550",
            "Byte-8": "0.8158512204",
            "Byte-9": "0.8163282409",
            "Byte-10": "0.8290346273",
            "Byte-11": "0.8178659319",
            "Byte-12": "0.8271661146",
            "Byte-13": "0.8179587373",
            "Byte-14": "0.8110555366",
            "Byte-15": "0.8226330221",
            "Byte-16": "0.8042387511",
            "Byte-17": "0.8089982523",
            "Byte-18": "0.8096778325",
            "Byte-19": "0.8119662558",
            "Byte-20": "0.8101688471",
            "Byte-21": "0.8135198726",
            "Byte-22": "0.8146499074",
            "Byte-23": "0.8155777779",
            "Byte-24": "0.8186385420",
            "Byte-25": "0.8200062528",
            "Byte-26": "0.8144485941",
            "Byte-27": "0.8224803030",
            "Byte-28": "0.8113706386",
            "Byte-29": "0.8161088888",
            "Byte-30": "0.8179285106",
            "Byte-31": "0.8275124932",
            "Byte-32": "0.9366932043",
            "Byte-33": "0.8052515824",
            "Byte-34": "0.8178447559",
            "Byte-35": "0.8212996390",
            "Byte-36": "0.8239991070",
            "Byte-37": "0.8147117394",
            "Byte-38": "0.8140197080",
            "Byte-39": "0.8242550336",
            "Byte-40": "0.8070932007",
            "Byte-41": "0.8152097333",
            "Byte-42": "0.8116049143",
            "Byte-43": "0.8226709957",
            "Byte-44": "0.8214054230",
            "Byte-45": "0.8247037463",
            "Byte-46": "0.8222290470",
            "Byte-47": "0.8252163700",
            "Byte-48": "0.8256159098",
            "Byte-49": "0.8374656853",
            "Byte-50": "0.8256908318",
            "Byte-51": "0.8278972685",
            "Byte-52": "0.8183495145",
            "Byte-53": "0.8292378920",
            "Byte-54": "0.8260674958",
            "Byte-55": "0.8328054470",
            "Byte-56": "0.8217898511",
            "Byte-57": "0.8254349525",
            "Byte-58": "0.8120560272",
            "Byte-59": "0.8266122627",
            "Byte-60": "0.8283207268",
            "Byte-61": "0.8196725408",
            "Byte-62": "0.8273377707",
            "Byte-63": "0.8328005352",
            "Byte-64": "0.7991561952",
            "Byte-65": "0.8068393477",
            "Byte-66": "0.8056819084",
            "Byte-67": "0.8143715364",
            "Byte-68": "0.8165215195",
            "Byte-69": "0.8178761275",
            "Byte-70": "0.8213235960",
            "Byte-71": "0.8256376083",
            "Byte-72": "0.8147875805",
            "Byte-73": "0.8274117256",
            "Byte-74": "0.8121549296",
            "Byte-75": "0.8200218110",
            "Byte-76": "0.8153865367",
            "Byte-77": "0.8232513458",
            "Byte-78": "0.8237437410",
            "Byte-79": "0.8323302605",
            "Byte-80": "0.8063808207",
            "Byte-81": "0.8099331962",
            "Byte-82": "0.8194171672",
            "Byte-83": "0.8243240713",
            "Byte-84": "0.8153337827",
            "Byte-85": "0.8198894047",
            "Byte-86": "0.8247472442",
            "Byte-87": "0.8237238536",
            "Byte-88": "0.8257621941",
            "Byte-89": "0.8155476016",
            "Byte-90": "0.8145019194",
            "Byte-91": "0.8227777628",
            "Byte-92": "0.8118928997",
            "Byte-93": "0.8178288808",
            "Byte-94": "0.8229854588",
            "Byte-95": "0.8306030641",
            "Byte-96": "0.8096945342",
            "Byte-97": "0.8600078951",
            "Byte-98": "0.8211063580",
            "Byte-99": "0.8643351360",
            "Byte-100": "0.8354426792",
            "Byte-101": "0.8927980429",
            "Byte-102": "0.8318732194",
            "Byte-103": "0.8375813112",
            "Byte-104": "0.8299588683",
            "Byte-105": "0.8651028314",
            "Byte-106": "0.8153874941",
            "Byte-107": "0.8349371169",
            "Byte-108": "0.8561539307",
            "Byte-109": "0.8443220395",
            "Byte-110": "0.8641076373",
            "Byte-111": "0.8801636640",
            "Byte-112": "0.8310880386",
            "Byte-113": "0.8187930354",
            "Byte-114": "0.8613697834",
            "Byte-115": "0.8537208379",
            "Byte-116": "0.8734036399",
            "Byte-117": "0.8377312029",
            "Byte-118": "0.8304669280",
            "Byte-119": "0.8325710459",
            "Byte-120": "0.8299902438",
            "Byte-121": "0.8388493772",
            "Byte-122": "0.8163872622",
            "Byte-123": "0.8246250416",
            "Byte-124": "0.8340314266",
            "Byte-125": "0.8219131903",
            "Byte-126": "0.8317767205",
            "Byte-127": "0.8356630572",
            "Byte-128": "0.7983907163",
            "Byte-129": "0.8014197062",
            "Byte-130": "0.8083447218",
            "Byte-131": "0.8150773853",
            "Byte-132": "0.8083133457",
            "Byte-133": "0.8137068891",
            "Byte-134": "0.8130868705",
            "Byte-135": "0.8168598128",
            "Byte-136": "0.8052618892",
            "Byte-137": "0.8150953426",
            "Byte-138": "0.8131308698",
            "Byte-139": "0.8274082533",
            "Byte-140": "0.8250427002",
            "Byte-141": "0.8291453727",
            "Byte-142": "0.8167271210",
            "Byte-143": "0.8258463053",
            "Byte-144": "0.8124179183",
            "Byte-145": "0.8184169507",
            "Byte-146": "0.8224804363",
            "Byte-147": "0.8228841641",
            "Byte-148": "0.8121677492",
            "Byte-149": "0.8184682504",
            "Byte-150": "0.8210980980",
            "Byte-151": "0.8198660706",
            "Byte-152": "0.8089228715",
            "Byte-153": "0.8152815750",
            "Byte-154": "0.8170017135",
            "Byte-155": "0.8222243000",
            "Byte-156": "0.8178708950",
            "Byte-157": "0.8210587094",
            "Byte-158": "0.8265343343",
            "Byte-159": "0.8320220307",
            "Byte-160": "0.7939016242",
            "Byte-161": "0.8045631709",
            "Byte-162": "0.8062839621",
            "Byte-163": "0.8158392532",
            "Byte-164": "0.8142942619",
            "Byte-165": "0.8133457212",
            "Byte-166": "0.8151018682",
            "Byte-167": "0.8241880791",
            "Byte-168": "0.8029400568",
            "Byte-169": "0.8134012573",
            "Byte-170": "0.8077811290",
            "Byte-171": "0.8184644565",
            "Byte-172": "0.8211615665",
            "Byte-173": "0.8207040428",
            "Byte-174": "0.8160069147",
            "Byte-175": "0.8275677468",
            "Byte-176": "0.8157114536",
            "Byte-177": "0.8332284164",
            "Byte-178": "0.8125363902",
            "Byte-179": "0.8182679623",
            "Byte-180": "0.8158383537",
            "Byte-181": "0.8174253095",
            "Byte-182": "0.8221981350",
            "Byte-183": "0.8256350600",
            "Byte-184": "0.8116464155",
            "Byte-185": "0.8177478300",
            "Byte-186": "0.8152036649",
            "Byte-187": "0.8235873467",
            "Byte-188": "0.8303486522",
            "Byte-189": "0.8227696182",
            "Byte-190": "0.8297481376",
            "Byte-191": "0.8350106190",
            "Byte-192": "0.8077271126",
            "Byte-193": "0.8177961022",
            "Byte-194": "0.8164525782",
            "Byte-195": "0.8243569742",
            "Byte-196": "0.8153376747",
            "Byte-197": "0.8161742205",
            "Byte-198": "0.8360981076",
            "Byte-199": "0.8242013380",
            "Byte-200": "0.8178668438",
            "Byte-201": "0.8266338574",
            "Byte-202": "0.8185438788",
            "Byte-203": "0.8248774570",
            "Byte-204": "0.8224305411",
            "Byte-205": "0.8212437223",
            "Byte-206": "0.8215829323",
            "Byte-207": "0.8300113998",
            "Byte-208": "0.7989041084",
            "Byte-209": "0.8140121370",
            "Byte-210": "0.8156966527",
            "Byte-211": "0.8256347457",
            "Byte-212": "0.8104840786",
            "Byte-213": "0.8144305223",
            "Byte-214": "0.8231445727",
            "Byte-215": "0.8235774162",
            "Byte-216": "0.8258208515",
            "Byte-217": "0.8172783141",
            "Byte-218": "0.8188545617",
            "Byte-219": "0.8257610174",
            "Byte-220": "0.8182642713",
            "Byte-221": "0.8227763756",
            "Byte-222": "0.8314920257",
            "Byte-223": "0.8356686514",
            "Byte-224": "0.8139285247",
            "Byte-225": "0.8264585812",
            "Byte-226": "0.8173617668",
            "Byte-227": "0.8217358260",
            "Byte-228": "0.8292362483",
            "Byte-229": "0.8288473187",
            "Byte-230": "0.8236198883",
            "Byte-231": "0.8262666314",
            "Byte-232": "0.8101629128",
            "Byte-233": "0.8207429278",
            "Byte-234": "0.8129491682",
            "Byte-235": "0.8241216945",
            "Byte-236": "0.8246044816",
            "Byte-237": "0.8219062260",
            "Byte-238": "0.8212204116",
            "Byte-239": "0.8357265232",
            "Byte-240": "0.8336914262",
            "Byte-241": "0.8244258638",
            "Byte-242": "0.8421227263",
            "Byte-243": "0.8296292710",
            "Byte-244": "0.8150527163",
            "Byte-245": "0.8204915609",
            "Byte-246": "0.8242934808",
            "Byte-247": "0.8307059870",
            "Byte-248": "0.8359204648",
            "Byte-249": "0.8408693464",
            "Byte-250": "0.8199396952",
            "Byte-251": "0.8301694530",
            "Byte-252": "0.8396832444",
            "Byte-253": "0.8277289905",
            "Byte-254": "0.8359186499",
            "Byte-255": "0.8510057438"
        }
    ]
}